LICENSE
README.md
setup.py
leanvector/__init__.py
leanvector/leanvector.py
leanvector/test.py
leanvector/test_credentials.py
leanvector.egg-info/PKG-INFO
leanvector.egg-info/SOURCES.txt
leanvector.egg-info/dependency_links.txt
leanvector.egg-info/requires.txt
leanvector.egg-info/top_level.txt